MANIFEST.in
setup.py
mantrid/__init__.py
mantrid/actions.py
mantrid/cli.py
mantrid/client.py
mantrid/config.py
mantrid/greenbody.py
mantrid/loadbalancer.py
mantrid/management.py
mantrid/socketmeld.py
mantrid/stats_socket.py
mantrid.egg-info/PKG-INFO
mantrid.egg-info/SOURCES.txt
mantrid.egg-info/dependency_links.txt
mantrid.egg-info/entry_points.txt
mantrid.egg-info/requires.txt
mantrid.egg-info/top_level.txt
mantrid/static/no-hosts.http
mantrid/static/test.http
mantrid/static/timeout.http
mantrid/static/unknown.http
mantrid/tests/__init__.py
mantrid/tests/actions.py
mantrid/tests/client.py
mantrid/tests/loadbalancer.py