Metadata-Version: 1.0
Name: mantrid
Version: 1.0.2
Summary: A pure-Python loadbalancer.
Home-page: http://github.com/epio/mantrid/
Author: Epio Limited
Author-email: team@ep.io
License: UNKNOWN
Platform: UNKNOWN
Classifier: Development Status :: 5 - Production/Stable
Classifier: License :: OSI Approved :: BSD License
Classifier: Programming Language :: Python
